{
	"map": {
		"id": 1,
		"name": "map",
		"row": 3,
		"col": 2,
		"tile": [
			[
				"assets/美术素材/assets/美术素材/index",
				"",
				""
			],
			[
				"",
				"",
				""
			]
		],
		"item": [
			[
				"php",
				"",
				""
			],
			[
				"",
				"",
				""
			]
		],
		"equipment": [
			[
				1,
				0,
				0
			],
			[
				0,
				0,
				0
			]
		],
		"walkable": [
			[
				2,
				0,
				0
			],
			[
				0,
				0,
				0
			]
		],
		"npc": [
			[
				3,
				0,
				0
			],
			[
				0,
				0,
				0
			]
		],
		"monster": [
			[
				4,
				0,
				0
			],
			[
				0,
				0,
				0
			]
		],
		"portal": [
			[
				5,
				0,
				0
			],
			[
				0,
				0,
				0
			]
		]
	}
}